englishidioms/L_algorithm.py
englishidioms/__init__.py
englishidioms/phrases.json
englishidioms/nltk_data/.DS_Store
englishidioms/nltk_data/corpora/.DS_Store
englishidioms/nltk_data/corpora/wordnet/LICENSE
englishidioms/nltk_data/corpora/wordnet/README
englishidioms/nltk_data/corpora/wordnet/adj.exc
englishidioms/nltk_data/corpora/wordnet/adv.exc
englishidioms/nltk_data/corpora/wordnet/citation.bib
englishidioms/nltk_data/corpora/wordnet/cntlist.rev
englishidioms/nltk_data/corpora/wordnet/data.adj
englishidioms/nltk_data/corpora/wordnet/data.adv
englishidioms/nltk_data/corpora/wordnet/data.noun
englishidioms/nltk_data/corpora/wordnet/data.verb
englishidioms/nltk_data/corpora/wordnet/index.adj
englishidioms/nltk_data/corpora/wordnet/index.adv
englishidioms/nltk_data/corpora/wordnet/index.noun
englishidioms/nltk_data/corpora/wordnet/index.sense
englishidioms/nltk_data/corpora/wordnet/index.verb
englishidioms/nltk_data/corpora/wordnet/lexnames
englishidioms/nltk_data/corpora/wordnet/noun.exc
englishidioms/nltk_data/corpora/wordnet/verb.exc
englishidioms/nltk_data/taggers/.DS_Store
englishidioms/nltk_data/taggers/averaged_perceptron_tagger/averaged_perceptron_tagger.pickle
englishidioms/nltk_data/tokenizers/.DS_Store
englishidioms/nltk_data/tokenizers/punkt/.DS_Store
englishidioms/nltk_data/tokenizers/punkt/README
englishidioms/nltk_data/tokenizers/punkt/czech.pickle
englishidioms/nltk_data/tokenizers/punkt/danish.pickle
englishidioms/nltk_data/tokenizers/punkt/dutch.pickle
englishidioms/nltk_data/tokenizers/punkt/english.pickle
englishidioms/nltk_data/tokenizers/punkt/estonian.pickle
englishidioms/nltk_data/tokenizers/punkt/finnish.pickle
englishidioms/nltk_data/tokenizers/punkt/french.pickle
englishidioms/nltk_data/tokenizers/punkt/german.pickle
englishidioms/nltk_data/tokenizers/punkt/greek.pickle
englishidioms/nltk_data/tokenizers/punkt/italian.pickle
englishidioms/nltk_data/tokenizers/punkt/malayalam.pickle
englishidioms/nltk_data/tokenizers/punkt/norwegian.pickle
englishidioms-0.1.0.dist-info/LICENSE
englishidioms-0.1.0.dist-info/METADATA
englishidioms-0.1.0.dist-info/WHEEL
englishidioms-0.1.0.dist-info/top_level.txt
englishidioms-0.1.0.dist-info/RECORD
