Metadata-Version: 2.1
Name: englishidioms
Version: 0.1.0
Summary: An efficient Python package for detecting and identifying English idiomatic expressions and phrases within sentences.
Author: Mahmoud Zaghloul
Classifier: Programming Language :: Python :: 3
Classifier: License :: OSI Approved :: MIT License
Classifier: Operating System :: OS Independent
Requires-Python: >=3.10
License-File: LICENSE
Requires-Dist: nltk ==3.8.1
